kiara_modules/core/__init__.py
kiara_modules/core/boolean.py
kiara_modules/core/date.py
kiara_modules/core/defaults.py
kiara_modules/core/dev.py
kiara_modules/core/dict.py
kiara_modules/core/file.py
kiara_modules/core/file_bundle.py
kiara_modules/core/generic.py
kiara_modules/core/import.py
kiara_modules/core/json.py
kiara_modules/core/list.py
kiara_modules/core/logic.py
kiara_modules/core/metadata_models.py
kiara_modules/core/operations.py
kiara_modules/core/py.typed
kiara_modules/core/python.py
kiara_modules/core/string.py
kiara_modules/core/value.py
kiara_modules/core/value_types.py
kiara_modules/core/yaml.py
kiara_modules/core/array/__init__.py
kiara_modules/core/array/utils.py
kiara_modules/core/bytes/__init__.py
kiara_modules/core/bytes/msgpack.py
kiara_modules/core/database/__init__.py
kiara_modules/core/database/query.py
kiara_modules/core/database/utils.py
kiara_modules/core/pipelines/.gitkeep
kiara_modules/core/pipelines/__init__.py
kiara_modules/core/pipelines/array/restore.json
kiara_modules/core/pipelines/logic/nand.json
kiara_modules/core/pipelines/logic/nor.json
kiara_modules/core/pipelines/logic/xor.json
kiara_modules/core/pipelines/table/filter/by_date.json
kiara_modules/core/resources/.gitkeep
kiara_modules/core/resources/templates/sqlite_schama.sql.j2
kiara_modules/core/table/__init__.py
kiara_modules/core/table/filter.py
kiara_modules/core/table/query.py
kiara_modules/core/table/utils.py
kiara_modules.core-0.3.6.dist-info/LICENSE
kiara_modules.core-0.3.6.dist-info/METADATA
kiara_modules.core-0.3.6.dist-info/WHEEL
kiara_modules.core-0.3.6.dist-info/entry_points.txt
kiara_modules.core-0.3.6.dist-info/top_level.txt
kiara_modules.core-0.3.6.dist-info/RECORD
